{
 "actions": [],
 "allow_rename": 1,
 "creation": "2024-09-12 12:51:37.341693",
 "doctype": "DocType",
 "editable_grid": 1,
 "engine": "InnoDB",
 "field_order": [
  "supplier",
  "item_code",
  "price"
 ],
 "fields": [
  {
   "fieldname": "supplier",
   "fieldtype": "Link",
   "in_list_view": 1,
   "in_preview": 1,
   "label": "Supplier",
   "options": "Supplier"
  },
  {
   "fieldname": "item_code",
   "fieldtype": "Link",
   "in_list_view": 1,
   "in_preview": 1,
   "label": "Item code",
   "options": "Item"
  },
  {
   "fieldname": "price",
   "fieldtype": "Int",
   "in_list_view": 1,
   "in_preview": 1,
   "label": "Price"
  }
 ],
 "index_web_pages_for_search": 1,
 "istable": 1,
 "links": [],
 "modified": "2024-09-12 12:55:24.163456",
 "modified_by": "Administrator",
 "module": "hms",
 "name": "Price List Items",
 "owner": "Administrator",
 "permissions": [],
 "sort_field": "modified",
 "sort_order": "DESC",
 "states": []
}